mkreports/__init__.py
mkreports/cli.py
mkreports/code_context.py
mkreports/config.py
mkreports/docs.py
mkreports/exceptions.py
mkreports/ipython.py
mkreports/page.py
mkreports/parser.py
mkreports/report.py
mkreports/settings.py
mkreports/tracker.py
mkreports/utils.py
mkreports/assets/code_admonition.css
mkreports/assets/download_buttons.css
mkreports/assets/min_max_filter.js
mkreports/md/__init__.py
mkreports/md/base.py
mkreports/md/combo.py
mkreports/md/containers.py
mkreports/md/docstring.py
mkreports/md/file.py
mkreports/md/handler.py
mkreports/md/header.py
mkreports/md/idstore.py
mkreports/md/image.py
mkreports/md/list.py
mkreports/md/md_proxy.py
mkreports/md/settings.py
mkreports/md/table.py
mkreports/md/text.py
mkreports-0.7.2.dist-info/entry_points.txt
mkreports-0.7.2.dist-info/LICENSE
mkreports-0.7.2.dist-info/WHEEL
mkreports-0.7.2.dist-info/METADATA
mkreports-0.7.2.dist-info/RECORD
