Metadata-Version: 2.1
Name: mkreports
Version: 0.7.2
Summary: A package to programmatically create mkdocs sites.
Author-email: Holger Hoefling <hhoeflin@gmail.com>
Requires-Python: >=3.8
Classifier: License :: OSI Approved :: MIT License
Requires-Dist: mkdocs >=1.2.3
Requires-Dist: mkdocs-material >=7.3.6
Requires-Dist: mdutils >=1.3.1
Requires-Dist: PyYAML >=6.0
Requires-Dist: immutabledict >=2.2.1
Requires-Dist: tabulate >=0.8.9
Requires-Dist: deepmerge >=0.3.0
Requires-Dist: python-frontmatter >=1.0.0
Requires-Dist: anytree >=2.8.0
Requires-Dist: intervaltree >=3.1.0
Requires-Dist: more-itertools >=8.12.0
Requires-Dist: typer >=0.4.0
Requires-Dist: mkdocstrings[python] >=0.17.0
Requires-Dist: GitPython >=3.1.26
Requires-Dist: parse >=1.19.0
Requires-Dist: importlib-resources >=5.4.0
Requires-Dist: sh
Requires-Dist: ipython >=7.30.1
Requires-Dist: pudb >=2021.2.2 ; extra == "dev"
Requires-Dist: bpython >=0.22.1 ; extra == "dev"
Requires-Dist: pytest >=6.2.5 ; extra == "dev"
Requires-Dist: pytest-pudb >=0.7.0 ; extra == "dev"
Requires-Dist: plotnine >=0.8.0 ; extra == "dev"
Requires-Dist: matplotlib >=3.4.3 ; extra == "dev"
Requires-Dist: plotly >=5.5.0 ; extra == "dev"
Requires-Dist: seaborn >=0.11.2 ; extra == "dev"
Requires-Dist: altair >=4.1.0 ; extra == "dev"
Requires-Dist: black ; extra == "dev"
Requires-Dist: flakehell ; extra == "dev"
Project-URL: Home, https://hhoeflin.github.io/mkreports/
Project-URL: Repository, https://github.com/hhoeflin/mkreports
Provides-Extra: dev
